{
  "php": {
    "LBL_RECYCLE_DELETE_ALL": "حذف تمام زباله‌ها",
    "RecycleBin": "سطل زباله"
  },
  "js": {
    "JS_MASS_DELETE": "حذف انبوه",
    "JS_MASS_ACTIVATE": "فعال سازی انبوه",
    "JS_DELETE_ALL_RECYCLE_RECORD": "حذف تمام سوابق از سطل بازیافت",
    "JS_ACTIVATE_RECORD_DESC": "Activating a record only changes the record's state without changing the rest of information. Are you sure you want to activate the record?",
    "JS_DELETE_ALL_RECYCLE_RECORD_DESC": "Deleting a record is permanent and irreversible for all record's information. Are you sure you want to delete the record?",
    "JS_ADDED_TO_QUEUE": "Added to the queue. All elements will be deleted"
  }
}