{
  "php": {
    "KnowledgeBase": "База знаний",
    "SINGLE_KnowledgeBase": "Знание",
    "BTN_KNOWLEDGE_BASE": "База знаний",
    "LBL_CUSTOM_INFORMATION": "Пользовательская информация",
    "FL_SUBJECT": "Предмет",
    "LBL_KNOWLEDGEBASE_INFORMATION": "Основная информация",
    "FL_CONTENT": "Содержание",
    "FL_CATEGORY": "Категория",
    "FL_VIEWS": "Просмотр",
    "PLL_PAGE": "Страница",
    "PLL_PRESENTATION": "Презентация",
    "LBL_VIEW_KNOWLEDGE_BASE": "База знаний",
    "LBL_PREVIOUS": "Предыдущий",
    "LBL_NEXT": "Следующий",
    "LBL_LIST_RECORDS": "Список записей",
    "FL_STATUS": "Статус",
    "LBL_RECORD_PREVIEW": "Предварительный просмотр",
    "PLL_DRAFT": "Черновик",
    "PLL_IN_REALIZATION": "На реализации",
    "PLL_OBJECTIONS": "Возражения",
    "PLL_FOR_APPROVAL": "На утверждении",
    "PLL_CANCELLED": "Отмененый",
    "PLL_ACCEPTED": "Принятый",
    "PLL_ARCHIVES": "Архивный",
    "LBL_ARTICLE": "Статья",
    "LBL_DESCRIPTION_BLOCK": "Описание",
    "LBL_ATTENTION_BLOCK": "Коментарии",
    "LBL_SIZE": "Размер",
    "FL_FEATURED": "Featured",
    "LBL_RELATED_KNOWLEDGE_BASES": "Related entries",
    "FL_INTRODUCTION": "Introduction",
    "ERR_NOT_ALLOWED": "Расширение файла не допустимо"
  }
}
