{
  "php": {
    "LBL_ADVANCED_PERMISSION": "Dodatna dovoljenja",
    "AdvancedPermission": "Dodatna dovoljenja",
    "LBL_ADVANCED_PERMISSION_DESCRIPTION": "Konfiguracija dovoljenja po meri, podelitev ali preklic dovoljenj za zapise.",
    "LBL_NAME": "Rule name",
    "LBL_MODULE": "Module",
    "LBL_ACTION": "Action",
    "LBL_STATUS": "Status",
    "LBL_ROLE": "Role",
    "LBL_MEMBERS": "Members",
    "LBL_PRIORITY": "Proiriteta",
    "FL_ACTIVE": "Active",
    "FL_INACTIVE": "Inactive",
    "FL_UNLOCK_RECORD": "Grant access",
    "FL_LOCK_RECORD": "Withdraw access",
    "LBL_SAVE_AND_CONDITIONS": "Next",
    "ERR_INACTIVE_ALERT_TITLE": "Dodatna dovoljenja so onemogočene",
    "ERR_INACTIVE_ALERT_DESC": "Change the  PERMITTED_BY_ADVANCED_PERMISSION  parameter in config\/security.php file to enable.",
    "LBL_RECALCULATE_PERMISSION_TITLE": "Permission recalculation",
    "LBL_RECALCULATE_PERMISSION_BTN": "Preračunavanje dovoljenj",
    "LBL_RECALCULATE_CRON_INFO": "Permission recalculations requires enabled CRON, please check if the task is active.",
    "LBL_MODULES_LIST": "Modules list",
    "ERR_INACTIVE_CACHING_PERM_ALERT_DESC": "Posebna dovoljenja so bila onemogočena, ker zahtevajo omogočanje predpomnjenja dovoljenj za zapis. Za dovoljenja za začetek dela morate omogočiti cron in nastaviti spremenljivko CACHING_PERMISSION_TO_RECORD [config \/ security.php] na true."
  }
}