{
  "php": {
    "Occurrences": "Faaliyetler",
    "SINGLE_Occurrences": "Faaliyet",
    "LBL_VIEW_CALENDAREXTENDED": "Grafik Takvim",
    "LBL_CUSTOM_INFORMATION": "Özel Bilgiler",
    "LBL_BASIC_INFORMATION": "Temel Bilgiler",
    "FL_TOPIC": "Konu",
    "FL_STATUS": "Durum",
    "FL_TYPE": "Tür",
    "FL_DATE_START": "Başlangıç tarihi",
    "FL_DATE_END": "Bitiş tarihi",
    "FL_DESCRIPTION": "Açıklama",
    "FL_PARTNERS": "Ortaklar",
    "FL_ATTENTION": "Yorum",
    "FL_LOCATION": "Yer",
    "FL_RATING": "Puanlama",
    "FL_NUMBER_OF_PARTICIPANTS": "Katılımcı sayısı",
    "FL_MEETING_URL": "Toplantı Linki",
    "PLL_TRAINING_OPEN": "Eğitim açık",
    "PLL_TRAINING_CLOSED": "Eğitim kapatıldı",
    "PLL_CONFERENCE": "Konferans",
    "PLL_WORKSHOPS": "Atölye Çalışmaları",
    "PLL_WEBINARS": "Web Seminerleri",
    "PLL_IN_REALIZATION": "Gerçekleşmede",
    "LBL_STATUS_REL": "Durum",
    "LBL_COMMENT_REL": "Yorum Yap",
    "PLL_REGISTERED": "Kayıtlı",
    "PLL_APPROVED": "Onaylandı",
    "PLL_PRESENT": "Mevcut",
    "PLL_ABSENT": "Yok",
    "LBL_USER_NAME": "Kullanıcı adı",
    "LBL_WORK_DAYS": "İş günleri",
    "LBL_GROUP_NAME": "Grup adı",
    "PLL_ACTIVE": "Aktif",
    "PLL_CANCELLED": "İptal edildi",
    "PLL_ARCHIVED": "Arşivlenen",
    "LBL_PARTICIPANT": "Katılımcı"
  }
}
