{
  "php": {
    "FCorectingInvoice": "Τιμολόγια διόρθωσης",
    "SINGLE_FCorectingInvoice": "Τιμολόγιo διόρθωσης",
    "LBL_CUSTOM_INFORMATION": "Πληροφορίες συστήματος",
    "LBL_INVOICE_ADDRESS": "Διεύθυνση τιμολογίου",
    "LBL_ADDRESS_DELIVERY_INFORMATION": "Διεύθυνση παράδοσης",
    "FL_SUBJECT": "Θέμα",
    "FL_PAYMENT_DATE": "Due date",
    "FL_SALE_DATE": "Ημερομηνία Πώλησης",
    "FL_FORM_PAYMENT": "Μέθοδος πληρωμής",
    "FL_BANK_ACCOUNT": "Αριθμός τραπεζικού λογαριασμού",
    "FL_NUMBER": "Αριθμός τιμολογίου",
    "FL_ACCOUNT": "Λογαριασμός",
    "FL_TOTAL": "Καθαρό ποσό",
    "FL_GROSS": "Μικτό ποσό",
    "FL_STATUS": "Κατάσταση",
    "PLL_CASH": "Μετρητά",
    "PLL_TRANSFER": "Τραπεζικό έμβασμα",
    "PLL_WIRE_TRANSFER": "Ηλεκτρονική μεταφορά",
    "LBL_YEAR": "Έτος",
    "FL_INVOICE": "Τιμολόγιο",
    "LBL_COMMENTS": "Σχόλια",
    "FL_EXTERNAL_COMMENT": "Εξωτερικό σχόλιο",
    "FL_INTERNAL_COMMENT": "Εξωτερικό σχόλιο",
    "LBL_BEFORE_CORRECTION": "Πριν από τη διόρθωση",
    "LBL_AFTER_CORRECTION": "Μετά τη διόρθωση",
    "LBL_CHOOSE_INVOICE": "Επιλέξτε τιμολόγιο που πρέπει να διορθωθεί",
    "LBL_COPY_FROM_INVOICE": "Αντιγραφή από το αρχικό τιμολόγιο",
    "LBL_INVOICE_INFO": "Πεδία αρχικού τιμολογίου - προ διορθώσεων.",
    "LBL_AFTER_INVOICE_INFO": "Πώς πρέπει θα είναι το τελικό τιμολόγιο μετά τη διόρθωση.",
    "LBL_AFTER_INVOICE_INFO_EDIT": "Πεδία Τιμολογίου που πρέπει να διορθωθούν. Αντιγράψτε όλα τα πεδία από το αρχικό τιμολόγιο και αλλάξτε τις τιμές, όπως απαιτείται."
  },
  "js": {
    "JS_FCORECTINGINVOICE_CHOOSE_INVOICE": "Επιλέξτε τιμολόγιο που πρέπει να διορθωθεί"
  }
}