{
  "php": {
    "SSingleOrders": "Παραγγελίες πωλήσεων",
    "SINGLE_SSingleOrders": "Παραγγελία πώλησης",
    "LBL_SSINGLEORDERS_INFORMATION": "Βασικές πληροφορίες",
    "LBL_CUSTOM_INFORMATION": "Πληροφορίες Συστήματος",
    "LBL_DESCRIPTION_INFORMATION": "Περιγραφή - Σχόλια",
    "LBL_STATISTICS": "Στατιστικά",
    "LBL_SUBJECT": "Θέμα",
    "LBL_NUMBER": "Αριθμός",
    "LBL_CLOSED_TIME": "Ώρα κλεισίματος",
    "LBL_STATUS": "Κατασταση",
    "LBL_REALIZATION_START_DATE": "Ημερομηνία έναρξης",
    "LBL_REALIZATION_COMPLETION_DATE": "Ημερομηνία ολοκλήρωσης",
    "LBL_ACTUAL_COMPLETION_DATE": "Ημερομηνία πραγματικής ολοκλήρωσης",
    "SINGLE_SSalesProcesses": "Ευκαιρία",
    "FL_TOTAL_PRICE": "Καθαρό σύνολο",
    "FL_MARGINP": "Συνολικό περιθώριο (%)",
    "FL_MARGIN": "Συνολικό περιθώριο",
    "FL_SUM_GROSS": "Ακαθάριστο ποσό",
    "FL_SUM_DISCOUNT": "Ποσό έκπτωσης",
    "FL_POS": "POS",
    "PLL_TRANSFER": "Μεταφορά",
    "FL_NUMBER_TABLE": "Αριθμός τραπεζιού",
    "FL_NUMBER_SEAT": "Αριθμός θέσης",
    "PLL_DRAFT": "Προσχέδιο",
    "PLL_IN_REALIZATION": "Σε υλοποίηση",
    "PLL_FOR_VERIFICATION": "Για επαλήθευση",
    "PLL_AWAITING_SIGNATURES": "Σε αναμονή υπογραφής",
    "PLL_CANCELLED": "Ακυρώθηκε",
    "PLL_ACCEPTED": "Έγινε Αποδοχή",
    "LBL_CHANGE_STATUS": "Αλλαγή κατάστασης",
    "LBL_SYNCHRONIZE_POS": "Συγχρονισμός POS",
    "FL_SOURCE": "Πηγή",
    "PLL_MANUAL": "Χειροκίνητα",
    "PLL_PORTAL": "Portal",
    "PLL_POS": "Point of sale",
    "PLL_MAGENTO": "Magento",
    "PLL_SHOP": "Κατάστημα",
    "FL_STORAGE": "Αποθ. χώρος",
    "FL_PAYMENT_STATUS": "Κατάσταση πληρωμής",
    "PLL_NOT_PAID": "Δεν πληρώθηκε",
    "PLL_PAID": "Πληρώθηκε",
    "PLL_OVERPAID": "Πληρώθηκε μεγαλύτερο ποσό",
    "PLL_UNDERPAID": "Πληρώθηκε μικρότερο ποσό",
    "FL_PARENT_SSINGLEORDERS": "Parent sales order",
    "FL_MAGENTO_STATUS": "Magento status",
    "PLL_PENDING": "Pending",
    "PLL_PENDING_PAYMENT": "Pending payment",
    "PLL_PENDING_PAYPAL": "Pending PayPal",
    "PLL_PROCESSING": "Processing",
    "PLL_HOLDED": "On hold",
    "PLL_FRAUD": "Suspected fraud",
    "PLL_PAYMENT_REVIEW": "Payment review",
    "PLL_PAYPAL_CANCELED_REVERSAL": "PayPal canceled reversal",
    "PLL_PAYPAL_REVERSED": "PayPal reversed",
    "PLL_CLOSED": "Closed",
    "PLL_COMPLETE": "Complete"
  }
}
