{
  "php": {
    "Occurrences": "Häufigkeit",
    "SINGLE_Occurrences": "Häufigkeit",
    "LBL_VIEW_CALENDAREXTENDED": "Grafischer Kalender",
    "LBL_CUSTOM_INFORMATION": "Eigene Informationen",
    "LBL_BASIC_INFORMATION": "Grundlegende Informationen",
    "FL_TOPIC": "Thema",
    "FL_STATUS": "Status",
    "FL_TYPE": "Typ",
    "FL_DATE_START": "Beginndatum",
    "FL_DATE_END": "Enddatum",
    "FL_DESCRIPTION": "Beschreibung",
    "FL_PARTNERS": "Partner",
    "FL_ATTENTION": "Bemerkungen",
    "FL_LOCATION": "Standort",
    "FL_RATING": "Bewertung",
    "FL_NUMBER_OF_PARTICIPANTS": "Anzahl der Teilnehmer",
    "FL_MEETING_UTL": "Meeting URL",
    "PLL_TRAINING_OPEN": "Training geöffnet",
    "PLL_TRAINING_CLOSED": "Training geschlossen",
    "PLL_CONFERENCE": "Konferenz",
    "PLL_WORKSHOPS": "Workshops",
    "PLL_WEBINARS": "Webinare",
    "PLL_IN_REALIZATION": "In Bearbeitung",
    "LBL_STATUS_REL": "Status",
    "LBL_COMMENT_REL": "Anmerkung",
    "PLL_REGISTERED": "Registriert",
    "PLL_APPROVED": "Genehmigt",
    "PLL_PRESENT": "Anwesend",
    "PLL_ABSENT": "Abwesend",
    "LBL_SELECT_USER_CALENDAR": "Benutzerkalender auswählen",
    "LBL_USER_NAME": "Benutzername",
    "LBL_WORK_DAYS": "Werktage",
    "LBL_SELECT_GROUP_CALENDAR": "Gruppenkalender auswählen",
    "LBL_GROUP_NAME": "Gruppenname",
    "PLL_ACTIVE": "Aktiv",
    "PLL_CANCELLED": "Abgesagt",
    "PLL_ARCHIVED": "Archiviert",
    "LBL_PARTICIPANT": "Teilnehmer"
  }
}
