{
  "php": {
    "Sharing Rules": "共享规则",
    "SharingAccess": "共享规则",
    "Accounts": "客户和联系人",
    "LBL_ADD_CUSTOM_RULE": "添加自定义规则",
    "LBL_ADD_CUSTOM_RULE_TO": "添加自定义规则",
    "LBL_ADVANCED_SHARING_RULES": "高级共享规则",
    "LBL_APPLY_NEW_SHARING_RULES": "应用新的共享规则",
    "LBL_CAN_ACCESSED_BY": "可以访问被",
    "LBL_CUSTOM_ACCESS_MESG": "没有自定义的访问规则",
    "LBL_MODULE": "模块",
    "LBL_PRIVILEGES": "权限",
    "LBL_READ": "只读",
    "LBL_READ_WRITE": "读和写",
    "LBL_RULE_NO": "规则编号",
    "LBL_SHARING_RULE": "共享规则",
    "LBL_WITH_PERMISSIONS": "权限",
    "Read Only": "只读",
    "Read Write": "可读\/可写",
    "SINGLE_Groups": "用户组",
    "Groups": "用户组",
    "SINGLE_RoleAndSubordinates": "角色和其下级",
    "RoleAndSubordinates": "角色和其下级",
    "SINGLE_Roles": "角色",
    "SINGLE_Users": "用户",
    "Roles": "角色",
    "Private": "私人",
    "Public: Read Only": "公开︰只读",
    "Public: Read, Create\/Edit, Delete": "公开︰ 读取、创建\/编辑、删除",
    "Public: Read, Create\/Edit": "公开︰ 读取、创建\/编辑、删除",
    "LBL_CUSTOM_RULE_SAVED_SUCCESSFULLY": "自定义共享规则已保存",
    "LBL_CUSTOM_RULE_SAVED_FAILED": "保存共享访问规则失败",
    "LBL_CUSTOM_RULE_DELETING_SUCCESSFULLY": "Custom sharing rule deleted successfully",
    "LBL_CUSTOM_RULE_DELETING_FAILED": "删除共享访问规则失败"
  },
  "js": {
    "JS_DEPENDENT_PRIVILEGES_SHOULD_CHANGE": "当客户访问权限设置为私有时，销售机会、服务单、报价单、销售订单和付款通知单付款通知单也必须设置为私有",
    "JS_NEW_SHARING_RULES_APPLIED_SUCCESSFULLY": "新共享规则已生效",
    "JS_SELECT_ANY_OTHER_ACCESSING_USER": "选择任何其他访问用户"
  }
}
