{
  "php": {
    "FInvoiceCost": "Obračun stroškov",
    "SINGLE_FInvoiceCost": "Obračun stroškov",
    "LBL_CUSTOM_INFORMATION": "Sistemski podatki",
    "LBL_INVOICE_ADDRESS": "Naslov računa",
    "LBL_ADDRESS_DELIVERY_INFORMATION": "Naslov dostave",
    "LBL_DESCRIPTION_BLOCK": "Opis",
    "LBL_ATTENTION_BLOCK": "Podatki o ",
    "FL_SUBJECT": "Zadeva",
    "FL_PAYMENT_DATE": "Datum zapadlosti",
    "FL_SALE_DATE": "Datum izdaje",
    "FL_FORM_PAYMENT": "Način plačila",
    "FL_BANK_ACCOUNT": "TRR",
    "FL_NUMBER": "Številka računa",
    "FL_ACCOUNT": "Račun",
    "FL_TOTAL": "Neto",
    "FL_GROSS": "Bruto",
    "FL_STATUS": "Status",
    "FL_PAYMENT_STATUS": "Status plačila",
    "FL_INVOICE_TYPE": "Vrsta računa",
    "FL_CATEGORY": "Kategorija",
    "PLL_CASH": "Gotovina",
    "PLL_TRANSFER": "Bančno nakazilo",
    "PLL_WIRE_TRANSFER": "Elektronki prenos",
    "PLL_AWAITING_PAYMENT": "Čakamo plačilo",
    "PLL_PARTIALLY_PAID": "Delno plačilo",
    "PLL_FULLY_PAID": "V celoti plačano",
    "PLL_DOMESTIC_INVOICE": "Račun doma",
    "PLL_FOREIGN_INVOICE": "Račun tujina",
    "PLL_IC_INVOICE": "Dobava blaga blaga znotraj družbe",
    "PLL_UNASSIGNED": "Neopredeljen",
    "PLL_AWAITING_REALIZATION": "Čakamo na realizacijo",
    "PLL_FOR_PROCESSING": "Za obdelat",
    "PLL_IN_PROGRESSING": "V realizaciji",
    "PLL_SUBMITTED_COMMENTS": "Predložene pripombe",
    "PLL_FOR_APPROVAL": "V odobritvi",
    "PLL_CANCELLED": "Prekinjeno",
    "PLL_ACCEPTED": "Odobreno"
  }
}