{
  "php": {
    "LBL_TRANSLATE": "Preklad",
    "LBL_COMPANY_VARIABLES": "Podrobnosti o firme",
    "LBL_CUSTOM_VARIABLES": "Vlastné premenné",
    "LBL_EMPLOYEE_NAME": "Meno zamestnanca",
    "LBL_CURRENT_DATE": "Aktuálny dátum",
    "LBL_CURRENT_TIME": "Aktuálny čas",
    "LBL_BASE_TIMEZONE": "Systém - časové pásmo",
    "LBL_USER_TIMEZONE": "Používateľ - časové pásmo",
    "LBL_SITE_URL": "URL stránky",
    "LBL_PORTAL_URL": "Portal URL",
    "LBL_CRM_DETAIL_VIEW_URL": "URL adresa záznamu v CRM",
    "LBL_ORGANIZATION": "Organizácia",
    "LBL_PORTAL_DETAIL_VIEW_URL": "Adresa URL záznamu v portáli",
    "LBL_RECORD_ID": "Záznam ID",
    "LBL_RECORD_LABEL": "Zaznamenajte štítok",
    "LBL_LIST_OF_CHANGES_IN_RECORD": "Zoznam zmien v zázname",
    "LBL_LIST_OF_NEW_VALUES_IN_RECORD": "Zoznam nových hodnôt v zázname",
    "LBL_RECORD_COMMENT": "Komentáre",
    "LBL_RELATED_RECORD_LABEL": "Súvisiaci záznamový štítok",
    "LBL_OWNER_EMAIL": "Majiteľ e-mailu",
    "LBL_MODULE_FIELDS": "Polia z modulu",
    "LBL_DEPENDENT_MODULE_FIELDS": "Polia od závislých modulov",
    "LBL_ADDITIONAL_VARIABLES": "Dodatočné premenné",
    "LBL_SOURCE_MODULE_FIELDS": "Polia zo zdrojového modulu",
    "LBL_ENTITY_VARIABLES": "Všeobecné premenné",
    "LBL_COPY_VALUE": "Hodnota poľa",
    "LBL_COPY_LABEL": "Názov poľa",
    "LBL_AUTOMATIC": "Automaticky",
    "LBL_RELATED_RECORDS_LIST": "Zoznam súvisiacich záznamov",
    "LBL_DATE_TODAY": "Dnes",
    "LBL_DATE_TOMORROW": "Zajtra",
    "LBL_DATE_YESTERDAY": "Včera",
    "LBL_DATE_FIRST_DAY_OF_THIS_WEEK": "Pondelok tento týždeň",
    "LBL_DATE_MONDAY_NEXT_WEEK": "Pondelok budúci týždeň",
    "LBL_DATE_FIRST_DAY_OF_THIS_MONTH": "Prvý deň tohto mesiaca",
    "LBL_DATE_LAST_DAY_OF_THIS_MONTH": "Posledný deň v tomto mesiaci",
    "LBL_DATE_FIRST_DAY_OF_NEXT_MONTH": "Prvý deň nasledujúceho mesiaca",
    "LBL_PRODUCTS_TABLE": "Tabuľka s rozšíreným blokom",
    "LBL_PRODUCTS_TABLE_DESCRIPTION": "Tabuľka s rozšíreným blokom a popisom",
    "LBL_PRODUCTS_TABLE_NEW": "Vylepšená tabuľka s rozšíreným blokom",
    "LBL_PRODUCTS_TABLE_RELATED_MODULE": "Tabuľka s rozšíreným blokom pre súvisiace moduly",
    "LBL_PRODUCTS_TABLE_CORRECTING_BEFORE": "Tabuľka s rozšíreným blokom - pred korekciou",
    "LBL_PRODUCTS_TABLE_IMAGES": "Stôl s rozšíreným blokom - spolu s fotografiou výrobkov",
    "LBL_PRODUCTS_TABLE_SHORT_VERSION": "Tabuľka s rozšíreným blokom - skrátená verzia",
    "LBL_PRODUCTS_TABLE_LONG_TWO_LANG": "Tabuľka s pokročilou blokovou verziou - dvojjazyčná dlhá verzia",
    "LBL_PRODUCTS_TABLE_LONG_VERSION": "Tabuľka s pokročilou blokovou verziou",
    "LBL_TABLE_CURRENCY_S_TWO_LANG": "Súhrn mien pre pokročilý blok - dvojjazyčná verzia",
    "LBL_TABLE_CURRENCY_SUMMARY": "Súhrn mien pre pokročilý blok",
    "LBL_TABLE_DISCOUNT_S_TWO_LANG": "Zhrnutie zliav pre pokročilý blok - dvojjazyčná verzia",
    "LBL_TABLE_TAX_S_TWO_LANG": "Súhrnná tabuľka daní - dvojjazyčná verzia",
    "LBL_TABLE_DISCOUNT_SUMMARY": "Zhrnutie zliav pre pokročilý blok",
    "LBL_OVERDUE_DEADLINES": "Udalosti po splatnosti",
    "LBL_TABLE_TAX_SUMMARY": "Súhrn dane za pokročilý blok",
    "LBL_ALL_PAGES": "Všetky stránky",
    "LBL_CURRENT_PAGE": "Aktuálna stránka",
    "LBL_INVENTORY_TABLE": "Tabuľka zásob s vlastnými preddefinovanými stĺpcami",
    "LBL_DYNAMIC_INVENTORY_TABLE": "Tabuľka zásob s dynamickými stĺpcami",
    "LBL_INVENTORY_VARIABLES": "Ďalšie premenné zásob",
    "LBL_TEXT_PARSER_RECORDS_LIST": "List of records",
    "LBL_TEXT_PARSER_USER_VARIABLE": "User variable",
    "LBL_REPORT_NEW_RECORDS": "New records in given module",
    "LBL_REPORT_SSALESPROCESSES": "Opportunity records",
    "LBL_REPORT_CALENDAR": "Calendar records",
    "LBL_REPORT_OVERDUE": "Overdue records",
    "LBL_REPORT_LOGIN_HISTORY": "Login history",
    "LBL_USER_RECORD_DUPLICATE_LIST": "User duplicated records list",
    "LBL_USER_RECORD_FILTERED_LIST": "User filtered records list",
    "LBL_SUMMARY_FIELDS": "List of fields visible in the summary"
  }
}
