{
  "php": {
    "LBL_ROOM_CRM": "Favorieten",
    "LBL_ROOM_GROUP": "Groepsgesprek",
    "LBL_ROOM_GLOBAL": "Globaal gesprek",
    "LBL_MESSAGE": "Voer hier uw bericht in. Druk op SHIFT + ENTER om een nieuwe regel toe te voegen.",
    "LBL_PARTICIPANTS": "Deelnemers",
    "LBL_SEARCH_PARTICIPANTS": "Zoek deelnemers",
    "LBL_SEARCH_MESSAGE": "Zoek berichten",
    "LBL_CREATE_CHAT_ROOM": "Maak een nieuwe gesprek",
    "LBL_REMOVE_FROM_FAVORITES": "Verwijder uit favorieten",
    "LBL_ADD_FROM_FAVORITES": "Voeg toe aan favorieten",
    "LBL_EARLIER": "Eerder",
    "LBL_NOTIFICATION": "Gespreksmeldingen",
    "LBL_SOUND_OFF": "Geluid uit",
    "LBL_SOUND_ON": "Geluid aan",
    "LBL_HISTORY_CHAT": "Gespreksgeschiedenis",
    "LBL_MORE": "meer",
    "LBL_HIDE": "verbergen",
    "LBL_NO_MESSAGES": "Geen berichten",
    "LBL_UNREAD": "Ongelezen",
    "LBL_ENTER": "Hiermee schakelt u het verzenden van berichten in nadat u op ENTER hebt gedrukt",
    "LBL_DETAIL_VIEW": "Detailweergave",
    "LBL_ROOM_DESCRIPTION_CRM": "Gesprekslijst met records gemarkeerd als favorieten",
    "LBL_ROOM_DESCRIPTION_GROUP": "Gesprekslijst met gebruikersgroepen",
    "LBL_ROOM_DESCRIPTION_GLOBAL": "Gesprekslijst zichtbaar voor alle gebruikers",
    "LBL_CHAT_USER_SWITCHED": "Gesprek is inactief als u bent overgeschakeld naar een andere gebruiker.",
    "LBL_CHAT_NEW_MESSAGE": "Nieuw bericht"
  }
}
