{
    "ar-SA": {
        "prefix": "ar-SA",
        "crowdinCode": "ar",
        "name": "Arabic",
        "progress": 5,
        "time": "2019-09-03 09:11:05"
    },
    "bg-BG": {
        "prefix": "bg-BG",
        "crowdinCode": "bg",
        "name": "Bulgarian",
        "progress": 39,
        "time": "2019-09-06 11:41:38"
    },
    "cs-CZ": {
        "prefix": "cs-CZ",
        "crowdinCode": "cs",
        "name": "Czech",
        "progress": 6,
        "time": "2019-09-06 11:42:20"
    },
    "da-DK": {
        "prefix": "da-DK",
        "crowdinCode": "da",
        "name": "Danish",
        "progress": 14,
        "time": "2019-05-09 09:07:58"
    },
    "de-DE": {
        "prefix": "de-DE",
        "crowdinCode": "de",
        "name": "German",
        "progress": 100,
        "time": "2019-09-03 09:13:17"
    },
    "el-GR": {
        "prefix": "el-GR",
        "crowdinCode": "el",
        "name": "Greek",
        "progress": 100,
        "time": "2019-09-03 09:13:37"
    },
    "es-ES": {
        "prefix": "es-ES",
        "crowdinCode": "es-ES",
        "name": "Spanish",
        "progress": 100,
        "time": "2019-09-03 09:16:39"
    },
    "fa-IR": {
        "prefix": "fa-IR",
        "crowdinCode": "fa",
        "name": "Persian",
        "progress": 10,
        "time": "2019-07-01 12:30:51"
    },
    "fr-FR": {
        "prefix": "fr-FR",
        "crowdinCode": "fr",
        "name": "French",
        "progress": 85,
        "time": "2019-08-12 10:04:59"
    },
    "it-IT": {
        "prefix": "it-IT",
        "crowdinCode": "it",
        "name": "Italian",
        "progress": 100,
        "time": "2019-09-04 14:37:06"
    },
    "ko-KR": {
        "prefix": "ko-KR",
        "crowdinCode": "ko",
        "name": "Korean",
        "progress": 19,
        "time": "2019-09-04 14:37:28"
    },
    "nl-BE": {
        "prefix": "nl-BE",
        "crowdinCode": "nl-BE",
        "name": "Dutch, Belgium",
        "progress": 18,
        "time": "2019-09-04 14:35:40"
    },
    "nl-NL": {
        "prefix": "nl-NL",
        "crowdinCode": "nl",
        "name": "Dutch",
        "progress": 23,
        "time": "2019-09-03 09:12:21"
    },
    "pl-PL": {
        "prefix": "pl-PL",
        "crowdinCode": "pl",
        "name": "Polish",
        "progress": 100,
        "time": "2019-09-03 09:14:51"
    },
    "pt-BR": {
        "prefix": "pt-BR",
        "crowdinCode": "pt-BR",
        "name": "Portuguese, Brazilian",
        "progress": 82,
        "time": "2019-09-03 09:15:28"
    },
    "pt-PT": {
        "prefix": "pt-PT",
        "crowdinCode": "pt-PT",
        "name": "Portuguese",
        "progress": 30,
        "time": "2019-09-03 09:15:10"
    },
    "ro-RO": {
        "prefix": "ro-RO",
        "crowdinCode": "ro",
        "name": "Romanian",
        "progress": 86,
        "time": "2019-08-12 10:08:19"
    },
    "ru-RU": {
        "prefix": "ru-RU",
        "crowdinCode": "ru",
        "name": "Russian",
        "progress": 93,
        "time": "2019-08-12 10:08:42"
    },
    "sk-SK": {
        "prefix": "sk-SK",
        "crowdinCode": "sk",
        "name": "Slovak",
        "progress": 6,
        "time": "2019-09-06 11:47:41"
    },
    "sl-SI": {
        "prefix": "sl-SI",
        "crowdinCode": "sl",
        "name": "Slovenian",
        "progress": 83,
        "time": "2019-09-06 11:48:02"
    },
    "tr-TR": {
        "prefix": "tr-TR",
        "crowdinCode": "tr",
        "name": "Turkish",
        "progress": 36,
        "time": "2019-05-09 09:15:13"
    },
    "uk-UA": {
        "prefix": "uk-UA",
        "crowdinCode": "uk",
        "name": "Ukrainian",
        "progress": 44,
        "time": "2019-05-09 09:15:44"
    },
    "zh-CN": {
        "prefix": "zh-CN",
        "crowdinCode": "zh-CN",
        "name": "Chinese Simplified",
        "progress": 8,
        "time": "2019-08-22 11:47:13"
    }
}