{
  "php": {
    "LBL_TRANSLATE": "Traduzione",
    "LBL_COMPANY_VARIABLES": "Campi dipartimento",
    "LBL_CUSTOM_VARIABLES": "Campi personalizzati",
    "LBL_EMPLOYEE_NAME": "Nome dipendente",
    "LBL_CURRENT_DATE": "Data corrente",
    "LBL_CURRENT_TIME": "Ora corrente",
    "LBL_BASE_TIMEZONE": "Fuso orario sistema",
    "LBL_USER_TIMEZONE": "Fuso orario utente",
    "LBL_SITE_URL": "Link CRM",
    "LBL_PORTAL_URL": "Link portale cliente",
    "LBL_CRM_DETAIL_VIEW_URL": "Link del record nel CRM",
    "LBL_ORGANIZATION": "Dipartimento",
    "LBL_PORTAL_DETAIL_VIEW_URL": "Link del record nel portale cliente",
    "LBL_RECORD_ID": "Identificativo record",
    "LBL_RECORD_LABEL": "Titolo / oggetto del record",
    "LBL_LIST_OF_CHANGES_IN_RECORD": "Lista delle modifiche del record",
    "LBL_LIST_OF_NEW_VALUES_IN_RECORD": "Lista dei nuovi valori del record",
    "LBL_RECORD_COMMENT": "Commenti",
    "LBL_RELATED_RECORD_LABEL": "Etichetta record relazionato",
    "LBL_OWNER_EMAIL": "Proprietario email",
    "LBL_MODULE_FIELDS": "Campi del modulo",
    "LBL_DEPENDENT_MODULE_FIELDS": "Campi dei moduli collegati (1:M)",
    "LBL_ADDITIONAL_VARIABLES": "Campi aggiuntivi",
    "LBL_SOURCE_MODULE_FIELDS": "Campi dal modulo sorgente",
    "LBL_ENTITY_VARIABLES": "Campi globali",
    "LBL_COPY_VALUE": "valore campo",
    "LBL_COPY_LABEL": "nome campo",
    "LBL_AUTOMATIC": "Automatico",
    "LBL_RELATED_RECORDS_LIST": "Moduli relazionati (M:M)",
    "LBL_DATE_TODAY": "Oggi",
    "LBL_DATE_TOMORROW": "Domani",
    "LBL_DATE_YESTERDAY": "Ieri",
    "LBL_DATE_FIRST_DAY_OF_THIS_WEEK": "Lunedì questa settimana",
    "LBL_DATE_MONDAY_NEXT_WEEK": "Lunedì prossimo settimana",
    "LBL_DATE_FIRST_DAY_OF_THIS_MONTH": "Primo giorno di questo mese",
    "LBL_DATE_LAST_DAY_OF_THIS_MONTH": "Ultimo giorno di questo mese",
    "LBL_DATE_FIRST_DAY_OF_NEXT_MONTH": "Primo giorno del mese prossimo",
    "LBL_PRODUCTS_TABLE": "Tabella con blocco esteso",
    "LBL_PRODUCTS_TABLE_DESCRIPTION": "Tabella con blocco esteso e descrizione",
    "LBL_PRODUCTS_TABLE_NEW": "Tabella migliorata con blocco esteso",
    "LBL_PRODUCTS_TABLE_RELATED_MODULE": "Tabella con blocco esteso per i moduli relazionati",
    "LBL_PRODUCTS_TABLE_CORRECTING_BEFORE": "Tabella con blocco esteso - prima della correzione",
    "LBL_PRODUCTS_TABLE_IMAGES": "Tabella con blocco esteso - insieme alla foto dei prodotti",
    "LBL_PRODUCTS_TABLE_SHORT_VERSION": "Tabella con blocco esteso - versione breve",
    "LBL_PRODUCTS_TABLE_LONG_TWO_LANG": "Tabella con blocco esteso - versione bilingue completa",
    "LBL_PRODUCTS_TABLE_LONG_VERSION": "Tabella con blocco esteso - versione completa",
    "LBL_TABLE_CURRENCY_S_TWO_LANG": "Sommario valuta per blocco esteso - versione bilingue",
    "LBL_TABLE_CURRENCY_SUMMARY": "Sommario valuta per blocco esteso",
    "LBL_TABLE_DISCOUNT_S_TWO_LANG": "Sommario sconto per blocco esteso - versione bilingue",
    "LBL_TABLE_TAX_S_TWO_LANG": "Tabella sommario tassazione - versione bilingue",
    "LBL_GROSS_AMOUNT_IN_WORDS": "Importo lordo in parole",
    "LBL_TABLE_DISCOUNT_SUMMARY": "Sommario sconto per il blocco esteso",
    "LBL_OVERDUE_DEADLINES": "Eventi scaduti",
    "LBL_TABLE_TAX_SUMMARY": "Sommario tasse per blocco esteso",
    "LBL_ALL_PAGES": "Tutte le pagine",
    "LBL_CURRENT_PAGE": "Pagina corrente",
    "LBL_INVENTORY_TABLE": "Tabella inventario con colonne predefinite personalizzate",
    "LBL_DYNAMIC_INVENTORY_TABLE": "Tabella inventario con colonne dinamiche",
    "LBL_INVENTORY_VARIABLES": "Variabili di inventario aggiuntive",
    "LBL_TEXT_PARSER_RECORDS_LIST": "List of records"
  }
}
